[
	{
		"name": "Temple cathare",
		"replaces": "Temple",
		"uniqueTo": "Cathare",
		"cost": 0,
		"hurryCostModifier": 25,
		"Faith": 2,
		"maintenance": 0,
		"requiredTech": "Philosophy",
		"greatPersonPoints": {"Great Prophet": 1},
		"uniques": ["Only available <when religion is enabled>"], 
		"requiredBuilding": "Shrine",
		"requiredTech": "Philosophy"
	},
	{
		"name": "Chateau de Montségur",
		"uniqueTo": "Cathare",
		"isWonder": true,
		"cityStrength": 10,
		"cityHealth": 25,
		"hurryCostModifier": 25,
		"requiredTech": "Chivalry",
		"uniques": ["Destroyed when the city is captured", "New [Military] units start with [15] Experience [in this city]","Free [Great General] appears","[+1 Faith] from [hill] tiles [in this city]"],
		"quote": "'La folie des croisades est ce qui à le plus honoré la raison humaine.'-Léon BLOY" 
	},
	
	
]
